setup.py
tornado_redis.egg-info/PKG-INFO
tornado_redis.egg-info/SOURCES.txt
tornado_redis.egg-info/dependency_links.txt
tornado_redis.egg-info/top_level.txt
tornadoredis/__init__.py
tornadoredis/client.py
tornadoredis/connection.py
tornadoredis/exceptions.py